odoo/addons/sale_order_line_sequence/README.rst
odoo/addons/sale_order_line_sequence/__init__.py
odoo/addons/sale_order_line_sequence/__manifest__.py
odoo/addons/sale_order_line_sequence/init_hooks.py
odoo/addons/sale_order_line_sequence/i18n/ca.po
odoo/addons/sale_order_line_sequence/i18n/de.po
odoo/addons/sale_order_line_sequence/i18n/el_GR.po
odoo/addons/sale_order_line_sequence/i18n/es.po
odoo/addons/sale_order_line_sequence/i18n/es_ES.po
odoo/addons/sale_order_line_sequence/i18n/es_VE.po
odoo/addons/sale_order_line_sequence/i18n/fi.po
odoo/addons/sale_order_line_sequence/i18n/fr.po
odoo/addons/sale_order_line_sequence/i18n/hr.po
odoo/addons/sale_order_line_sequence/i18n/hr_HR.po
odoo/addons/sale_order_line_sequence/i18n/hu.po
odoo/addons/sale_order_line_sequence/i18n/it.po
odoo/addons/sale_order_line_sequence/i18n/nl.po
odoo/addons/sale_order_line_sequence/i18n/nl_NL.po
odoo/addons/sale_order_line_sequence/i18n/pt.po
odoo/addons/sale_order_line_sequence/i18n/pt_BR.po
odoo/addons/sale_order_line_sequence/i18n/ro.po
odoo/addons/sale_order_line_sequence/i18n/sale_order_line_sequence.pot
odoo/addons/sale_order_line_sequence/i18n/sk.po
odoo/addons/sale_order_line_sequence/i18n/sl.po
odoo/addons/sale_order_line_sequence/i18n/tr.po
odoo/addons/sale_order_line_sequence/i18n/tr_TR.po
odoo/addons/sale_order_line_sequence/i18n/vi_VN.po
odoo/addons/sale_order_line_sequence/i18n/zh_CN.po
odoo/addons/sale_order_line_sequence/model/__init__.py
odoo/addons/sale_order_line_sequence/model/sale_order.py
odoo/addons/sale_order_line_sequence/readme/CONTRIBUTORS.rst
odoo/addons/sale_order_line_sequence/readme/CREDITS.rst
odoo/addons/sale_order_line_sequence/readme/DESCRIPTION.rst
odoo/addons/sale_order_line_sequence/static/description/icon.png
odoo/addons/sale_order_line_sequence/static/description/index.html
odoo/addons/sale_order_line_sequence/views/report_saleorder.xml
odoo/addons/sale_order_line_sequence/views/sale_view.xml
odoo12_addon_sale_order_line_sequence-12.0.1.0.0.99.dev18.dist-info/METADATA
odoo12_addon_sale_order_line_sequence-12.0.1.0.0.99.dev18.dist-info/WHEEL
odoo12_addon_sale_order_line_sequence-12.0.1.0.0.99.dev18.dist-info/top_level.txt
odoo12_addon_sale_order_line_sequence-12.0.1.0.0.99.dev18.dist-info/RECORD
